{
    "bw_terran": {
        "name": "BW Terran",
        "short_name": "T1",
        "aliases": [
            "스1 테란",
            "SC1人类"
        ],
        "is_bw_race": true,
        "is_sc2_race": false
    },
    "bw_zerg": {
        "name": "BW Zerg",
        "short_name": "Z1",
        "aliases": [
            "스1 저그",
            "SC1异虫"
        ],
        "is_bw_race": true,
        "is_sc2_race": false
    },
    "bw_protoss": {
        "name": "BW Protoss",
        "short_name": "P1",
        "aliases": [
            "스1 토스",
            "SC1星灵"
        ],
        "is_bw_race": true,
        "is_sc2_race": false
    },
    "sc2_terran": {
        "name": "SC2 Terran",
        "short_name": "T2",
        "aliases": [
            "테란",
            "人类",
            "Терраны"
        ],
        "is_bw_race": false,
        "is_sc2_race": true
    },
    "sc2_zerg": {
        "name": "SC2 Zerg",
        "short_name": "Z2",
        "aliases": [
            "저그",
            "异虫",
            "Зерги"
        ],
        "is_bw_race": false,
        "is_sc2_race": true
    },
    "sc2_protoss": {
        "name": "SC2 Protoss",
        "short_name": "P2",
        "aliases": [
            "토스",
            "星灵",
            "Протоссы"
        ],
        "is_bw_race": false,
        "is_sc2_race": true
    }
}